liqpay_api/__init__.py
liqpay_api/client.py
liqpay_api/utils.py
liqpay_api-0.1.2.dist-info/METADATA
liqpay_api-0.1.2.dist-info/WHEEL
liqpay_api-0.1.2.dist-info/licenses/LICENSE
liqpay_api-0.1.2.dist-info/RECORD
