Metadata-Version: 2.4
Name: liqpay-api
Version: 0.1.2
Summary: Asynchronous LiqPay SDK
Author-email: oldnum <oldnum@ukr.net>
License: MIT
License-File: LICENSE
Keywords: asyncio,liqpay,payments,python-sdk
Requires-Python: >=3.10
Requires-Dist: aiohttp>=3.8.0
Provides-Extra: dev
Requires-Dist: pytest; extra == 'dev'
Requires-Dist: pytest-asyncio; extra == 'dev'
